{
  "problem_set_id": "bab73a03-097c-4033-97d3-fa7a88a8d63b",
  "student_id": "16",
  "lesson_id": "49",
  "course_id": "7",
  "generated_at": "2026-05-18T20:38:01.856902",
  "questions": [
    {
      "id": "a1f3c9e2-4b7d-4e12-9f6a-2d5c8b7e1a3f",
      "topic": "Variable Assignment and Naming",
      "title": "Create a Personal Info Dictionary",
      "scenario_framing": "Imagine you are filling out a simple profile card for a classroom display. Each piece of information needs a clear label and a correctly typed value.",
      "problem_statement": "Write a function `build_profile(name, age, height_cm, is_student)` that returns a dictionary with keys \"name\", \"age\", \"height_cm\", and \"is_student\" mapped to the provided arguments. Ensure the types are:\n- name: string\n- age: integer\n- height_cm: float\n- is_student: boolean\nIf any argument is not of the expected type, raise a `TypeError` with an informative message.",
      "starter_code": "def build_profile(name, age, height_cm, is_student):\n    \"\"\"TODO: implement the profile builder as described.\"\"\"\n    pass",
      "rubric": [
        {
          "name": "Correctness",
          "description": "Returns a dictionary with exact keys and values of correct types.",
          "weight": 40
        },
        {
          "name": "Type Validation",
          "description": "Raises TypeError for mismatched input types with clear messages.",
          "weight": 30
        },
        {
          "name": "Code Clarity",
          "description": "Uses clear variable names and concise logic.",
          "weight": 20
        },
        {
          "name": "Edge Cases",
          "description": "Handles edge cases such as empty strings or zero values appropriately.",
          "weight": 10
        }
      ],
      "hints": [
        "Check each argument's type before constructing the dictionary.",
        "Use `isinstance` to verify types; raise an error if a check fails.",
        "After validation, create the dictionary literal with the four key‑value pairs and return it."
      ],
      "analogy_explanation": "Think of the dictionary as a labeled storage box: each label (key) tells you exactly what kind of item (value) belongs inside, just like a drawer marked \"Socks\" only holds socks, not shirts.",
      "difficulty": "easy",
      "target_weakness": null,
      "language": "python"
    },
    {
      "id": "d4e6b2f9-8c1a-4f3b-9d7e-5a6c0b9e2d4a",
      "topic": "Type Conversion",
      "title": "Convert Mixed Input to Uniform Numeric List",
      "scenario_framing": "You are preparing data for a simple bar chart. The raw data comes as a mix of strings and numbers that need to be unified into floats for consistent plotting.",
      "problem_statement": "Implement `normalize_numbers(values)` that takes a list containing integers, floats, and numeric strings (e.g., \"3\", \"4.5\"). Return a new list where every element is a float. If an element cannot be converted, skip it.",
      "starter_code": "def normalize_numbers(values):\n    \"\"\"TODO: convert each element to float when possible, skipping non‑numeric items.\"\"\"\n    pass",
      "rubric": [
        {
          "name": "Correct Conversion",
          "description": "All numeric values are correctly converted to float.",
          "weight": 35
        },
        {
          "name": "Skipping Invalid Items",
          "description": "Non‑numeric entries are omitted without causing errors.",
          "weight": 30
        },
        {
          "name": "Order Preservation",
          "description": "The order of successfully converted items matches the original list order.",
          "weight": 20
        },
        {
          "name": "Code Simplicity",
          "description": "Uses concise and readable constructs (e.g., list comprehensions).",
          "weight": 15
        }
      ],
      "hints": [
        "Iterate through the list and try converting each element to float.",
        "Use a try/except block around `float(item)` to catch conversion errors.",
        "Collect successful conversions into a new list and return it."
      ],
      "analogy_explanation": "Imagine you have a tray of different‑shaped cookies, and you need all of them to be the same size to fit a box. You reshape (convert) each edible cookie, and any that crumble (cannot convert) are simply left out of the box.",
      "difficulty": "medium",
      "target_weakness": "type conversion",
      "language": "python"
    },
    {
      "id": "9b7c1e3a-5f2d-4a9e-8c3b-1d6e0f4a7b2c",
      "topic": "String Operations and Formatting",
      "title": "Generate a Formatted Report Line",
      "scenario_framing": "A teacher wants a neat, fixed‑width line for each student’s test score to print on a console screen.",
      "problem_statement": "Write `format_score(name, score)` that returns a string where `name` is left‑justified in a field of width 12, and `score` is right‑justified in a field of width 5 with two decimal places. Example: `format_score(\"Alex\", 93.5)` should return `'Alex        93.50'`.",
      "starter_code": "def format_score(name, score):\n    \"\"\"TODO: return the formatted string as described.\"\"\"\n    pass",
      "rubric": [
        {
          "name": "Formatting Accuracy",
          "description": "Name and score appear in correct column widths and alignment.",
          "weight": 45
        },
        {
          "name": "Decimal Precision",
          "description": "Score is displayed with exactly two decimal places.",
          "weight": 25
        },
        {
          "name": "Robustness",
          "description": "Handles names longer than 12 characters by truncating or adjusting gracefully.",
          "weight": 20
        },
        {
          "name": "Readability",
          "description": "Uses clear string formatting methods.",
          "weight": 10
        }
      ],
      "hints": [
        "Consider Python's format specifications for alignment and width.",
        "Use an f‑string or `str.format` with `<` for left and `>` for right alignment.",
        "Remember to specify `.2f` for two decimal places on the score."
      ],
      "analogy_explanation": "Think of a bookshelf where each book slot has a fixed width. You place the title on the left side of the slot and the price on the right side, ensuring everything lines up neatly across all shelves.",
      "difficulty": "easy",
      "target_weakness": null,
      "language": "python"
    },
    {
      "id": "f2a9d4c1-3e7b-4d9f-8a2c-6b5e1f8d3c9a",
      "topic": "Boolean Logic and Conditional Expressions",
      "title": "Eligibility Checker for a Youth Event",
      "scenario_framing": "A community center needs a quick check to see if a teenager qualifies for a special weekend event based on age and parental consent.",
      "problem_statement": "Create `is_eligible(age, has_consent)` that returns `True` if the participant is between 13 and 17 inclusive **and** has parental consent (`has_consent` is True). Return `False` otherwise.",
      "starter_code": "def is_eligible(age, has_consent):\n    \"\"\"TODO: implement the eligibility logic as described.\"\"\"\n    pass",
      "rubric": [
        {
          "name": "Logical Correctness",
          "description": "Accurately implements the age range and consent condition.",
          "weight": 50
        },
        {
          "name": "Return Type",
          "description": "Always returns a Boolean value.",
          "weight": 20
        },
        {
          "name": "Edge Cases",
          "description": "Correctly handles boundary ages 13 and 17.",
          "weight": 20
        },
        {
          "name": "Simplicity",
          "description": "Uses a clear, single return statement if possible.",
          "weight": 10
        }
      ],
      "hints": [
        "Both conditions must be true at the same time.",
        "Check that `age` is >= 13 and <= 17, then combine with `has_consent` using `and`.",
        "A single line: `return 13 <= age <= 17 and has_consent`."
      ],
      "analogy_explanation": "Think of a two‑gate security checkpoint: you need the right badge (age range) *and* the green light from a supervisor (consent) to pass through.",
      "difficulty": "easy",
      "target_weakness": null,
      "language": "python"
    }
  ],
  "submissions": {
    "a1f3c9e2-4b7d-4e12-9f6a-2d5c8b7e1a3f": {
      "code": "def build_profile(name, age, height_cm, is_student):\n    \"\"\"TODO: implement the profile builder as described.\"\"\" s\n    pass  ",
      "hints_used": 0,
      "submitted_at": "2026-05-18T20:40:13.138011",
      "result": {
        "raw_score": 4,
        "hint_penalty": 0,
        "final_score": 4,
        "passed": false,
        "feedback": "The submitted code is only a placeholder and does not implement the required functionality. You need to construct the dictionary and add explicit type checks that raise informative TypeError messages. Once implemented, also consider handling edge cases like empty strings or zero values.",
        "rubric_scores": [
          {
            "criterion": "Correctness",
            "score": 0,
            "comment": "The function does not return any dictionary; it only contains a pass statement."
          },
          {
            "criterion": "Type Validation",
            "score": 0,
            "comment": "No type checks are performed, so TypeError is never raised."
          },
          {
            "criterion": "Code Clarity",
            "score": 20,
            "comment": "The function signature and docstring are present, but the implementation is missing."
          },
          {
            "criterion": "Edge Cases",
            "score": 0,
            "comment": "Edge cases such as empty strings or zero values are not addressed."
          }
        ],
        "mistake_tags": [
          "missing implementation",
          "no type checking"
        ],
        "hint_to_show": "Create the dictionary with the given keys and values, then verify each argument's type using isinstance and raise TypeError with a clear message if a mismatch occurs."
      }
    },
    "d4e6b2f9-8c1a-4f3b-9d7e-5a6c0b9e2d4a": {
      "code": "def normalize_numbers(values):ss\n    \"\"\"TODO: convert each element to float when possible, skipping non‑numeric items.\"\"\"\n    pass",
      "hints_used": 0,
      "submitted_at": "2026-05-18T20:41:25.392584",
      "result": {
        "raw_score": 0,
        "hint_penalty": 0,
        "final_score": 0,
        "passed": false,
        "feedback": "The submitted code is incomplete and contains a syntax error (the stray 'ss' after the function header). Implement the conversion logic, handling errors with try/except or a list comprehension, and ensure invalid items are omitted while preserving order.",
        "rubric_scores": [
          {
            "criterion": "Correct Conversion",
            "score": 0,
            "comment": "The function does not perform any conversion; it only contains a pass statement."
          },
          {
            "criterion": "Skipping Invalid Items",
            "score": 0,
            "comment": "No logic is present to detect or skip non‑numeric entries."
          },
          {
            "criterion": "Order Preservation",
            "score": 0,
            "comment": "Since no items are processed, the original order cannot be preserved."
          },
          {
            "criterion": "Code Simplicity",
            "score": 0,
            "comment": "The implementation is missing; there is no use of concise constructs."
          }
        ],
        "mistake_tags": [
          "syntax error",
          "missing implementation",
          "no conversion logic"
        ],
        "hint_to_show": "Use a list comprehension with a try/except block to convert each element to float and skip those that raise an exception."
      }
    },
    "9b7c1e3a-5f2d-4a9e-8c3b-1d6e0f4a7b2c": {
      "code": "def format_score(name, score):\n    \"\"\"TODO: return the formatted string as described.\"\"\"\n    pass  s",
      "hints_used": 0,
      "submitted_at": "2026-05-18T20:43:21.331616",
      "result": {
        "raw_score": 0,
        "hint_penalty": 0,
        "final_score": 0,
        "passed": false,
        "feedback": "The submitted code is incomplete and contains a syntax error, so it does not fulfill any of the problem requirements. Implement the function using proper string formatting to meet the specified column widths and decimal precision.",
        "rubric_scores": [
          {
            "criterion": "Formatting Accuracy",
            "score": 0,
            "comment": "The function does not return any string, so name and score are never placed in the required columns."
          },
          {
            "criterion": "Decimal Precision",
            "score": 0,
            "comment": "No formatting of the score is performed; the required two‑decimal display is missing."
          },
          {
            "criterion": "Robustness",
            "score": 0,
            "comment": "The code does not handle names longer than 12 characters because it never processes the input."
          },
          {
            "criterion": "Readability",
            "score": 0,
            "comment": "The implementation is absent and contains a syntax error, providing no readable formatting logic."
          }
        ],
        "mistake_tags": [
          "syntax error",
          "missing implementation",
          "placeholder code"
        ],
        "hint_to_show": "Use an f‑string like: return f\"{name:<12}{score:5.2f}\" to achieve the required alignment and precision."
      }
    },
    "f2a9d4c1-3e7b-4d9f-8a2c-6b5e1f8d3c9a": {
      "code": "def is_eligible(age, has_consent):\n    \"\"\"TODO: implement the  seligibility logic as described.\"\"\"\n    pass",
      "hints_used": 0,
      "submitted_at": "2026-05-18T20:44:45.119272",
      "result": {
        "raw_score": 0,
        "hint_penalty": 0,
        "final_score": 0,
        "passed": false,
        "feedback": "The function is currently a stub and does not perform any checks, returning None for all inputs. Implement the eligibility logic and ensure a Boolean is returned for every case. A single return statement can satisfy all criteria.",
        "rubric_scores": [
          {
            "criterion": "Logical Correctness",
            "score": 0,
            "comment": "The function contains only a pass statement and does not implement any eligibility logic."
          },
          {
            "criterion": "Return Type",
            "score": 0,
            "comment": "The function returns None (the default for a pass) instead of a Boolean."
          },
          {
            "criterion": "Edge Cases",
            "score": 0,
            "comment": "No handling of boundary ages 13 or 17 is present."
          },
          {
            "criterion": "Simplicity",
            "score": 0,
            "comment": "There is no return statement; the solution is not implemented."
          }
        ],
        "mistake_tags": [
          "missing implementation",
          "always returns None"
        ],
        "hint_to_show": "Replace the pass with: return 13 <= age <= 17 and has_consent"
      }
    }
  }
}